jupyterlab_form_js/__init__.py
jupyterlab_form_js/_frontend.py
jupyterlab_form_js/_version.py
jupyterlab_form_js/form.py
jupyterlab_form_js/labextension/package.json
jupyterlab_form_js/labextension/static/0.a1a7e2d8508cd35c1aed.js
jupyterlab_form_js/labextension/static/0.a1a7e2d8508cd35c1aed.js.LICENSE.txt
jupyterlab_form_js/labextension/static/480.1a74e4bd0c77800737f5.js
jupyterlab_form_js/labextension/static/568.27b9cce130a7e75bd857.js
jupyterlab_form_js/labextension/static/752.d54102e71409a5310798.js
jupyterlab_form_js/labextension/static/remoteEntry.888aaefe8d00a7bbcffc.js
jupyterlab_form_js/labextension/static/style.js
jupyterlab_form_js/labextension/static/third-party-licenses.json
jupyterlab_form_js/nbextension/extension.js
jupyterlab_form_js/nbextension/index.js
jupyterlab_form_js/nbextension/index.js.LICENSE.txt
jupyterlab_form_js/nbextension/index.js.map
jupyterlab_form_js/tests/__init__.py
jupyterlab_form_js/tests/conftest.py
jupyterlab_form_js/tests/test_form.py
jupyterlab_form_js/tests/test_nbextension_path.py
jupyterlab_form_js-0.1.3.data/data/share/jupyter/labextensions/jupyterlab-form-js/package.json
jupyterlab_form_js-0.1.3.data/data/share/jupyter/labextensions/jupyterlab-form-js/static/0.a1a7e2d8508cd35c1aed.js
jupyterlab_form_js-0.1.3.data/data/share/jupyter/labextensions/jupyterlab-form-js/static/0.a1a7e2d8508cd35c1aed.js.LICENSE.txt
jupyterlab_form_js-0.1.3.data/data/share/jupyter/labextensions/jupyterlab-form-js/static/480.1a74e4bd0c77800737f5.js
jupyterlab_form_js-0.1.3.data/data/share/jupyter/labextensions/jupyterlab-form-js/static/568.27b9cce130a7e75bd857.js
jupyterlab_form_js-0.1.3.data/data/share/jupyter/labextensions/jupyterlab-form-js/static/752.d54102e71409a5310798.js
jupyterlab_form_js-0.1.3.data/data/share/jupyter/labextensions/jupyterlab-form-js/static/remoteEntry.888aaefe8d00a7bbcffc.js
jupyterlab_form_js-0.1.3.data/data/share/jupyter/labextensions/jupyterlab-form-js/static/style.js
jupyterlab_form_js-0.1.3.dist-info/METADATA
jupyterlab_form_js-0.1.3.dist-info/WHEEL
jupyterlab_form_js-0.1.3.dist-info/licenses/LICENSE.txt
jupyterlab_form_js-0.1.3.dist-info/RECORD
